biplane.py
biplane-1.0.4.dist-info/METADATA
biplane-1.0.4.dist-info/WHEEL
biplane-1.0.4.dist-info/licenses/LICENSE.txt
biplane-1.0.4.dist-info/RECORD
