Metadata-Version: 2.1
Name: biplane
Version: 1.0.4
Summary: Minimal, fast, robust HTTP server library for Python/CircuitPython that uses non-blocking concurrent I/O even when asyncio isn't available!
Project-URL: Homepage, https://github.com/Uberi/biplane/
Project-URL: Bug Tracker, https://github.com/Uberi/biplane/issues
Author-email: Uberi <me@anthonyz.ca>
License-File: LICENSE.txt
Classifier: License :: OSI Approved :: MIT License
Classifier: Operating System :: OS Independent
Classifier: Programming Language :: Python :: 3
Requires-Python: >=3.7
